kinetic_bip_utils/__init__.py
kinetic_bip_utils/_version.py
kinetic_bip_utils/addr/__init__.py
kinetic_bip_utils/addr/ada_byron_addr.py
kinetic_bip_utils/addr/ada_shelley_addr.py
kinetic_bip_utils/addr/addr_dec_utils.py
kinetic_bip_utils/addr/addr_key_validator.py
kinetic_bip_utils/addr/algo_addr.py
kinetic_bip_utils/addr/atom_addr.py
kinetic_bip_utils/addr/avax_addr.py
kinetic_bip_utils/addr/bch_addr_converter.py
kinetic_bip_utils/addr/egld_addr.py
kinetic_bip_utils/addr/eos_addr.py
kinetic_bip_utils/addr/ergo_addr.py
kinetic_bip_utils/addr/eth_addr.py
kinetic_bip_utils/addr/fil_addr.py
kinetic_bip_utils/addr/iaddr_decoder.py
kinetic_bip_utils/addr/iaddr_encoder.py
kinetic_bip_utils/addr/icx_addr.py
kinetic_bip_utils/addr/nano_addr.py
kinetic_bip_utils/addr/near_addr.py
kinetic_bip_utils/addr/neo_addr.py
kinetic_bip_utils/addr/okex_addr.py
kinetic_bip_utils/addr/one_addr.py
kinetic_bip_utils/addr/P2PKH_addr.py
kinetic_bip_utils/addr/P2SH_addr.py
kinetic_bip_utils/addr/P2TR_addr.py
kinetic_bip_utils/addr/P2WPKH_addr.py
kinetic_bip_utils/addr/sol_addr.py
kinetic_bip_utils/addr/substrate_addr.py
kinetic_bip_utils/addr/trx_addr.py
kinetic_bip_utils/addr/xlm_addr.py
kinetic_bip_utils/addr/xmr_addr.py
kinetic_bip_utils/addr/xrp_addr.py
kinetic_bip_utils/addr/xtz_addr.py
kinetic_bip_utils/addr/zil_addr.py
kinetic_bip_utils/algorand/__init__.py
kinetic_bip_utils/algorand/mnemonic/__init__.py
kinetic_bip_utils/algorand/mnemonic/algorand_entropy_generator.py
kinetic_bip_utils/algorand/mnemonic/algorand_mnemonic.py
kinetic_bip_utils/algorand/mnemonic/algorand_mnemonic_decoder.py
kinetic_bip_utils/algorand/mnemonic/algorand_mnemonic_encoder.py
kinetic_bip_utils/algorand/mnemonic/algorand_mnemonic_generator.py
kinetic_bip_utils/algorand/mnemonic/algorand_mnemonic_utils.py
kinetic_bip_utils/algorand/mnemonic/algorand_mnemonic_validator.py
kinetic_bip_utils/algorand/mnemonic/algorand_seed_generator.py
kinetic_bip_utils/base58/__init__.py
kinetic_bip_utils/base58/base58.py
kinetic_bip_utils-0.0.1.dist-info/WHEEL
kinetic_bip_utils-0.0.1.dist-info/METADATA
kinetic_bip_utils-0.0.1.dist-info/RECORD
