Metadata-Version: 2.1
Name: kinetic-bip-utils
Version: 0.0.1
Summary: 
License: MIT
Keywords: solana,blockchain,kin,web3
Author: Antoni Oktha Fernandes
Author-email: 37358597+DesKaOne@users.noreply.github.com
Requires-Python: >=3.8,<4.0
Classifier: Intended Audience :: Developers
Classifier: License :: OSI Approved :: MIT License
Classifier: Natural Language :: English
Classifier: Programming Language :: Python :: 3
Classifier: Programming Language :: Python :: 3.8
Classifier: Programming Language :: Python :: 3.9
Classifier: Programming Language :: Python :: 3.10
Classifier: Programming Language :: Python :: 3.11
Classifier: Programming Language :: Python :: 3.7
Classifier: Programming Language :: Python :: 3.8
Classifier: Programming Language :: Python :: 3.9
Requires-Dist: cbor2 (>=5.1,<6.0)
Requires-Dist: crcmod (>=1.7,<2.0)
Requires-Dist: ecdsa (>=0.15,<1.0)
Requires-Dist: ed25519-blake2b (>=1.4,<2.0)
Requires-Dist: py-sr25519-bindings (>=0.1.3,<2.0.0)
Requires-Dist: pycryptodome (>=3.6,<4.0)
Requires-Dist: pynacl (>=1.4,<2.0)
